nsone/__init__.py
nsone-0.9.100.dist-info/DESCRIPTION.rst
nsone-0.9.100.dist-info/METADATA
nsone-0.9.100.dist-info/RECORD
nsone-0.9.100.dist-info/WHEEL
nsone-0.9.100.dist-info/metadata.json
nsone-0.9.100.dist-info/top_level.txt
