Metadata-Version: 2.0
Name: nsone
Version: 0.9.100
Summary: Legacy Python SDK for the NS1 DNS platform
Home-page: https://github.com/ns1/nsone-python
Author: NS1 Developers
Author-email: devteam@ns1.com
License: MIT
Platform: UNKNOWN
Requires-Dist: ns1-python
